{
    "普通":{
        "急行":[
            "获取先锋和辅助干员的精英化材料。如果能熟练运用先锋和辅助职业的话应该会在这场战斗中更加有利。<医疗符文>部署在其上的干员会持续恢复生命"
        ],
        "解锁条件":[
            "2星通关1-10 残留"
        ],
        "推荐等级":[
            "LV.40"
        ],
        "作战消耗":{
            "理智":"18"
        },
        "演习消耗":{
            "演习券":"1"
        },
        "部署上限":[
            "8"
        ],
        "初始COST":[
            "0"
        ],
        "COST上限":[
            "99"
        ],
        "目标点耐久":[
            "5"
        ],
        "敌人数量":[
            "46"
        ],
        "最短用时":[
            "2分25秒"
        ],
        "首次掉落":{
            "至纯源石":"三星获得"
        },
        "常规掉落":{
            "先锋芯片":"概率掉落",
            "辅助芯片":"概率掉落"
        },
        "特殊地形效果":[
            "医疗符文部署在其上的干员每秒持续恢复3%最大生命值"
        ],
        "地图":{
            "PR-C-1 急行 地图.png":"http://ak.mooncell.wiki/data:image/gif;base64,R0lGODlhAQABAAD/ACwAAAAAAQABAAACADs="
        }
    }
}