{
    "敌方装置":{
        "霜冻废墟":[
            "在某场战役中被大面积冻结的废墟，依旧有少数敌人及失控的源石生物徘徊。偶尔能看见不合时节的雪花飞舞。"
        ],
        "解锁条件":[
            "—"
        ],
        "推荐等级":[
            "—"
        ],
        "作战消耗":{
            "理智":"0"
        },
        "演习消耗":[
            "无法演习"
        ],
        "部署上限":[
            "9"
        ],
        "初始COST":[
            "10"
        ],
        "COST上限":[
            "99"
        ],
        "目标点耐久":[
            "2"
        ],
        "敌人数量":[
            "51"
        ],
        "最短用时":[
            "4分10秒"
        ],
        "地图":{
            "龙门外环 霜冻废墟 地图.png":"http://ak.mooncell.wiki/data:image/gif;base64,R0lGODlhAQABAAD/ACwAAAAAAQABAAACADs="
        }
    }
}